README.txt
bootstrap.py
buildout.cfg
setup.cfg
setup.py
docs/HISTORY.txt
docs/INSTALL.txt
docs/LICENSE.GPL
docs/LICENSE.txt
src/opkode/__init__.py
src/opkode.rateablediscussion.egg-info/PKG-INFO
src/opkode.rateablediscussion.egg-info/SOURCES.txt
src/opkode.rateablediscussion.egg-info/dependency_links.txt
src/opkode.rateablediscussion.egg-info/entry_points.txt
src/opkode.rateablediscussion.egg-info/namespace_packages.txt
src/opkode.rateablediscussion.egg-info/not-zip-safe
src/opkode.rateablediscussion.egg-info/paster_plugins.txt
src/opkode.rateablediscussion.egg-info/requires.txt
src/opkode.rateablediscussion.egg-info/top_level.txt
src/opkode/rateablediscussion/__init__.py
src/opkode/rateablediscussion/configure.zcml
src/opkode/rateablediscussion/interfaces.py
src/opkode/rateablediscussion/tests.py
src/opkode/rateablediscussion/browser/__init__.py
src/opkode/rateablediscussion/browser/ajax.py
src/opkode/rateablediscussion/browser/comments.pt
src/opkode/rateablediscussion/browser/comments.py
src/opkode/rateablediscussion/browser/configure.zcml
src/opkode/rateablediscussion/browser/interfaces.py
src/opkode/rateablediscussion/browser/javascripts/rateable.js
src/opkode/rateablediscussion/browser/stylesheets/main.css
src/opkode/rateablediscussion/profiles/default/browserlayer.xml
src/opkode/rateablediscussion/profiles/default/cssregistry.xml
src/opkode/rateablediscussion/profiles/default/jsregistry.xml
src/opkode/rateablediscussion/profiles/default/metadata.xml