Metadata-Version: 1.0
Name: opkode.rateablediscussion
Version: 0.1a2
Summary: Allows plone.app.discussion comments to be rated.
Home-page: http://opkode.net
Author: JC Brand
Author-email: jc@opkode.com
License: GPL
Keywords: discussion comment rating
Platform: UNKNOWN
Classifier: Framework :: Plone
Classifier: Programming Language :: Python
